asimov_cogwheel/__init__.py
asimov_cogwheel/__main__.py
asimov_cogwheel/asimov.py
asimov_cogwheel/asimov_template.yaml
asimov_cogwheel/config.py
asimov_cogwheel/data.py
asimov_cogwheel-0.1.1.dist-info/METADATA
asimov_cogwheel-0.1.1.dist-info/WHEEL
asimov_cogwheel-0.1.1.dist-info/entry_points.txt
asimov_cogwheel-0.1.1.dist-info/top_level.txt
asimov_cogwheel-0.1.1.dist-info/RECORD
