Metadata-Version: 2.4
Name: asimov-cogwheel
Version: 0.1.1
Summary: An asimov interface to the cogwheel parameter estimation code.
Author-email: Daniel Williams <daniel.williams@ligo.org>
License-Expression: MIT
Classifier: Programming Language :: Python :: 3
Classifier: Operating System :: OS Independent
Requires-Python: >=3.8
Requires-Dist: click
Requires-Dist: asimov>=0.6.1
Requires-Dist: lalsuite>=7.14
Requires-Dist: pesummary
Requires-Dist: nbconvert
Requires-Dist: bilby
Provides-Extra: docs
Requires-Dist: sphinx; extra == "docs"
Requires-Dist: kentigern; extra == "docs"
